verilog_files/Lab_5_Code/lab5_comp.v
module comp_sign(
input signed [3:0] A,
input signed [3:0] B,
output wire Gt, Eq, Lt);

assign Gt = (A > B) ? 1'b1 : 1'b0;
assign Eq = (A==B) ? 1'b1 : 1'b0;
assign Lt = (A < B) ? 1'b1 : 1'b0;

endmodule

verilog_files/Lab_5_Code/lab5_comp_tb.v
`timescale 1ns/1ns
`include "lab5_comp.v"
module lab5_comp_tb;
reg [3:0] A;
reg [3:0] B;
wire Gt, Eq, Lt;
comp_sign uut(.A(A), .B(B), .Gt(Gt), .Eq(Eq), .Lt(Lt));
initial begin
 $dumpfile("lab5_comp_tb.vcd");
 $dumpvars(0, lab5_comp_tb);
 // 3 Gt cases
A = 4'b0001; B = 4'b1111; // 1 > -1
#20;
A = 4'b1111; B = 4'b1110; // -1 > -2
#20;
A = 4'b0111; B = 4'b0010; // 7 > 2
#20;

 // 3 Eq cases
A = 4'b1001; B = 4'b1001; // -7 == -7
#20;
A = 4'b0011; B = 4'b0011; //  3 == 3
#20;
A = 4'b1111; B = 4'b1111; // -1 == -1
#20;

 // 3 Lt cases
A = 4'b1111; B = 4'b0001;  // -1 < 1
#20;
A = 4'b1110; B = 4'b1111; // -2 < -1
#20;
A = 4'b0010; B = 4'b0111; // 2 < 7
#20;
 end
endmodule

verilog_files/Lab_5_Code/lab5_comp_tb.vcd
$date
	Tue Jul 13 13:04:23 2021
$end
$version
	Icarus Verilog
$end
$timescale
	1ns
$end
$scope module lab5_comp_tb $end
$var wire 1 ! Lt $end
$var wire 1 " Gt $end
$var wire 1 # Eq $end
$var reg 4 $ A [3:0] $end
$var reg 4 % B [3:0] $end
$scope module uut $end
$var wire 4 & A [3:0] $end
$var wire 4 ' B [3:0] $end
$var wire 1 ! Lt $end
$var wire 1 " Gt $end
$var wire 1 # Eq $end
$upscope $end
$upscope $end
$enddefinitions $end
#0
$dumpvars
b1111 '
b1 &
b1111 %
b1 $
0#
1"
0!
$end
#20
b1110 %
b1110 '
b1111 $
b1111 &
#40
b10 %
b10 '
b111 $
b111 &
#60
1#
0"
b1001 %
b1001 '
b1001 $
b1001 &
#80
b11 %
b11 '
b11 $
b11 &
#100
b1111 %
b1111 '
b1111 $
b1111 &
#120
0#
1!
b1 %
b1 '
#140
b1111 %
b1111 '
b1110 $
b1110 &
#160
b111 %
b111 '
b10 $
b10 &
