verilog_files/Lab_5_Code/lab5_multireg.v
module mfreg(
input clk,
input [3:0] I,
input rst, ld, shr, shl, shin,
output [3:0] Q);

reg [3:0] R;

always @(posedge clk) begin
	if(rst == 1'b1) begin
		R <= 4'b0000;
	end
	else if(ld == 1'b1) begin
		R <= I;
	end
	else if(shr == 1'b1) begin
		R[3] <= shin; R[2] <= R[3]; R[1] <= R[2]; R[0] <= R[1];
	end
	else if(shl == 1'b1) begin
		R[3] <= R[2]; R[2] <= R[1]; R[1] <= R[0]; R[0] <= shin;
	end
end

assign Q = R;

endmodule;

verilog_files/Lab_5_Code/lab5_multireg_tb.v
`timescale 1ns/1ns
`include "lab5_multireg.v"
module lab5_multireg_tb;

reg clk;
reg [3:0] I;
reg rst, ld, shr, shl, shin;
reg [3:0] A;
wire [3:0] Q;
mfreg uut( .clk(clk), .I(I), .rst(rst), .ld(ld), .shr(shr), .shl(shl), .shin(shin), .Q(Q));
always #5 clk=~clk;
initial begin
 $dumpfile("lab5_multireg_tb.vcd");
 $dumpvars(0, lab5_multireg_tb);
 clk=0;
 assign A = 4'b1010;
 //Load A
 I = A;
 rst = 0; ld = 1; shr = 0; shl = 0; shin = 0;
 #10;
 
 ld = 0; rst = 1;
 #10;
 
 ld = 1; rst = 0;
 #25;
 
 //Right shift in 0111
 ld = 0; shr = 1; shin = 1;
 #10;

 shin = 1;
 #10;

 shin = 1;
 #10;

 shin = 0;
 #10;
 
 //Left shift in 1110
 shr = 0; shl = 1; shin = 1;
 #10;

 shin = 1;
 #10;

 shin = 1;
 #10;

 shin = 0;
 #10;
 $finish;
end
endmodule

verilog_files/Lab_5_Code/lab5_multireg_tb.vcd
$date
	Wed Jul 14 19:00:21 2021
$end
$version
	Icarus Verilog
$end
$timescale
	1ns
$end
$scope module lab5_multireg_tb $end
$var wire 4 ! Q [3:0] $end
$var reg 4 " A [3:0] $end
$var reg 4 # I [3:0] $end
$var reg 1 $ clk $end
$var reg 1 % ld $end
$var reg 1 & rst $end
$var reg 1 ' shin $end
$var reg 1 ( shl $end
$var reg 1 ) shr $end
$scope module uut $end
$var wire 4 * I [3:0] $end
$var wire 4 + Q [3:0] $end
$var wire 1 $ clk $end
$var wire 1 % ld $end
$var wire 1 & rst $end
$var wire 1 ' shin $end
$var wire 1 ( shl $end
$var wire 1 ) shr $end
$var reg 4 , R [3:0] $end
$upscope $end
$upscope $end
$enddefinitions $end
#0
$dumpvars
bx ,
bx +
b1010 *
0)
0(
0'
0&
1%
0$
b1010 #
b1010 "
bx !
$end
#5
b1010 !
b1010 +
b1010 ,
1$
#10
0$
1&
0%
#15
b0 !
b0 +
b0 ,
1$
#20
0$
0&
1%
#25
b1010 !
b1010 +
b1010 ,
1$
#30
0$
#35
1$
#40
0$
#45
b1101 !
b1101 +
b1101 ,
1$
1'
1)
0%
#50
0$
#55
b1110 !
b1110 +
b1110 ,
1$
#60
0$
#65
b1111 !
b1111 +
b1111 ,
1$
#70
0$
#75
b111 !
b111 +
b111 ,
1$
0'
#80
0$
#85
b1111 !
b1111 +
b1111 ,
1$
1'
1(
0)
#90
0$
#95
1$
#100
0$
#105
1$
#110
0$
#115
b1110 !
b1110 +
b1110 ,
1$
0'
#120
0$
#125
b1100 !
b1100 +
b1100 ,
1$
