verilog_files/Lab_6_Code/lab6_regfile.v
module regfile(
input wire [1:0] RAddr, WAddr,
input wire Ren, Wen,
input wire [31:0] WData,
input wire Rst, Clk,
output reg [31:0] RData );

reg [31:0] regfile [0:3];

always @(posedge Clk) begin
	if(Rst == 1'b1) begin
		regfile[0] <= 32'd0;
		regfile[1] <= 32'd0;
		regfile[2] <= 32'd0;
		regfile[3] <= 32'd0;
	end
	else if(Wen == 1'b1) begin
		regfile[WAddr] <= WData;
	end
end

always @(*) begin
	if(Ren == 1'b1) begin
		RData = regfile[RAddr];
	end
	else begin
		RData = 32'hzzz_zzzz;
	end
end

endmodule

verilog_files/Lab_6_Code/lab6_regfile_tb.v
`timescale 1ns/1ns
`include "lab6_regfile.v"
module lab6_regfile_tb;

reg [1:0] RAddr, WAddr;
reg Ren, Wen;
reg [31:0] WData;
reg Rst, Clk;
wire [31:0] RData;

regfile uut( .Clk(Clk), .RAddr(RAddr), .WAddr(WAddr), .Ren(Ren),
 .Wen(Wen), .WData(WData), .Rst(Rst), .RData(RData));
always #5 Clk=~Clk;
initial begin
 $dumpfile("lab6_regfile_tb.vcd");
 $dumpvars(0, lab6_regfile_tb);
 Clk=0;
 Rst = 0;
 Ren = 0;
 RAddr = 0; 
 WAddr = 2'b00;
 WData = 15;
 Wen = 1;
 #20;
 WAddr = 2'b01;
 WData = 103;
 #20;
 WAddr = 2'b10;
 WData = 34;
 #20;
 WAddr = 2'b11;
 WData = 123;
 #20;
 
 Wen = 0; 
 RAddr = 2'b00;
 Ren = 1;
 #20;
 RAddr = 2'b11;
 #20;
 Ren = 0;
 Rst = 1;
 #20;
 Rst = 0; 
 RAddr = 2'b01;
 Ren = 1;
 #20;
 $finish;
end
endmodule

verilog_files/Lab_6_Code/lab6_regfile_tb.vcd
$date
	Thu Jul 15 12:00:39 2021
$end
$version
	Icarus Verilog
$end
$timescale
	1ns
$end
$scope module lab6_regfile_tb $end
$var wire 32 ! RData [31:0] $end
$var reg 1 " Clk $end
$var reg 2 # RAddr [1:0] $end
$var reg 1 $ Ren $end
$var reg 1 % Rst $end
$var reg 2 & WAddr [1:0] $end
$var reg 32 ' WData [31:0] $end
$var reg 1 ( Wen $end
$scope module uut $end
$var wire 1 " Clk $end
$var wire 2 ) RAddr [1:0] $end
$var wire 1 $ Ren $end
$var wire 1 % Rst $end
$var wire 2 * WAddr [1:0] $end
$var wire 32 + WData [31:0] $end
$var wire 1 ( Wen $end
$var reg 32 , RData [31:0] $end
$upscope $end
$upscope $end
$enddefinitions $end
#0
$dumpvars
bz ,
b1111 +
b0 *
b0 )
1(
b1111 '
b0 &
0%
0$
b0 #
0"
bz !
$end
#5
1"
#10
0"
#15
1"
#20
0"
b1100111 '
b1100111 +
b1 &
b1 *
#25
1"
#30
0"
#35
1"
#40
0"
b100010 '
b100010 +
b10 &
b10 *
#45
1"
#50
0"
#55
1"
#60
0"
b1111011 '
b1111011 +
b11 &
b11 *
#65
1"
#70
0"
#75
1"
#80
b1111 !
b1111 ,
0"
1$
0(
#85
1"
#90
0"
#95
1"
#100
b1111011 !
b1111011 ,
0"
b11 #
b11 )
#105
1"
#110
0"
#115
1"
#120
bz !
bz ,
0"
1%
0$
#125
1"
#130
0"
#135
1"
#140
b0 !
b0 ,
0"
1$
b1 #
b1 )
0%
