verilog_files/Lab_6_Code/lab6_timer.v
module timerst(
input wire clk, load, enable,
input wire [31:0] M, output tick );

reg [31:0] register;
always @(posedge clk) begin
	if(load == 1'b1) begin
		register <= M - 32'd1;
	end
end

wire [31:0] dcounterin;
assign dcounterin = (load == 1'b1) ? M - 32'd1 : register;

reg [31:0] downcounter;
always @(posedge clk) begin
	if((load == 1'b1) || (tick == 1'b1)) begin
		downcounter <= dcounterin;
	end
	else if (enable == 1'b1) begin
		downcounter <= downcounter - 32'd1;
	end
end

assign tick = (downcounter == 32'd0) ? 1'b1 : 1'b0;

endmodule

verilog_files/Lab_6_Code/lab6_timer_tb.v
`timescale 1ns/1ns
`include "lab6_timer.v"
module lab6_timer_tb;

reg clk, load, enable;
reg [31:0] M;
wire tick;

timerst uut( .clk(clk), .load(load), .enable(enable), .M(M), .tick(tick));
always #1 clk=~clk;
initial begin
 $dumpfile("lab6_timer_tb.vcd");
 $dumpvars(0, lab6_timer_tb);
 clk=0;
 load = 1;
 enable = 0;
 M = 182;
 #100;
 load = 0; enable = 1;
 #1000;
 load = 1; 
 #5;
 load = 0;
 #500;
 $finish;
end
endmodule

verilog_files/Lab_6_Code/lab6_timer_tb.vcd
$date
	Thu Jul 15 12:01:08 2021
$end
$version
	Icarus Verilog
$end
$timescale
	1ns
$end
$scope module lab6_timer_tb $end
$var wire 1 ! tick $end
$var reg 32 " M [31:0] $end
$var reg 1 # clk $end
$var reg 1 $ enable $end
$var reg 1 % load $end
$scope module uut $end
$var wire 32 & M [31:0] $end
$var wire 1 # clk $end
$var wire 1 $ enable $end
$var wire 1 % load $end
$var wire 1 ! tick $end
$var wire 32 ' dcounterin [31:0] $end
$var reg 32 ( downcounter [31:0] $end
$var reg 32 ) register [31:0] $end
$upscope $end
$upscope $end
$enddefinitions $end
#0
$dumpvars
bx )
bx (
b10110101 '
b10110110 &
1%
0$
0#
b10110110 "
x!
$end
#1
0!
b10110101 )
b10110101 (
1#
#2
0#
#3
1#
#4
0#
#5
1#
#6
0#
#7
1#
#8
0#
#9
1#
#10
0#
#11
1#
#12
0#
#13
1#
#14
0#
#15
1#
#16
0#
#17
1#
#18
0#
#19
1#
#20
0#
#21
1#
#22
0#
#23
1#
#24
0#
#25
1#
#26
0#
#27
1#
#28
0#
#29
1#
#30
0#
#31
1#
#32
0#
#33
1#
#34
0#
#35
1#
#36
0#
#37
1#
#38
0#
#39
1#
#40
0#
#41
1#
#42
0#
#43
1#
#44
0#
#45
1#
#46
0#
#47
1#
#48
0#
#49
1#
#50
0#
#51
1#
#52
0#
#53
1#
#54
0#
#55
1#
#56
0#
#57
1#
#58
0#
#59
1#
#60
0#
#61
1#
#62
0#
#63
1#
#64
0#
#65
1#
#66
0#
#67
1#
#68
0#
#69
1#
#70
0#
#71
1#
#72
0#
#73
1#
#74
0#
#75
1#
#76
0#
#77
1#
#78
0#
#79
1#
#80
0#
#81
1#
#82
0#
#83
1#
#84
0#
#85
1#
#86
0#
#87
1#
#88
0#
#89
1#
#90
0#
#91
1#
#92
0#
#93
1#
#94
0#
#95
1#
#96
0#
#97
1#
#98
0#
#99
1#
#100
0#
1$
0%
#101
b10110100 (
1#
#102
0#
#103
b10110011 (
1#
#104
0#
#105
b10110010 (
1#
#106
0#
#107
b10110001 (
1#
#108
0#
#109
b10110000 (
1#
#110
0#
#111
b10101111 (
1#
#112
0#
#113
b10101110 (
1#
#114
0#
#115
b10101101 (
1#
#116
0#
#117
b10101100 (
1#
#118
0#
#119
b10101011 (
1#
#120
0#
#121
b10101010 (
1#
#122
0#
#123
b10101001 (
1#
#124
0#
#125
b10101000 (
1#
#126
0#
#127
b10100111 (
1#
#128
0#
#129
b10100110 (
1#
#130
0#
#131
b10100101 (
1#
#132
0#
#133
b10100100 (
1#
#134
0#
#135
b10100011 (
1#
#136
0#
#137
b10100010 (
1#
#138
0#
#139
b10100001 (
1#
#140
0#
#141
b10100000 (
1#
#142
0#
#143
b10011111 (
1#
#144
0#
#145
b10011110 (
1#
#146
0#
#147
b10011101 (
1#
#148
0#
#149
b10011100 (
1#
#150
0#
#151
b10011011 (
1#
#152
0#
#153
b10011010 (
1#
#154
0#
#155
b10011001 (
1#
#156
0#
#157
b10011000 (
1#
#158
0#
#159
b10010111 (
1#
#160
0#
#161
b10010110 (
1#
#162
0#
#163
b10010101 (
1#
#164
0#
#165
b10010100 (
1#
#166
0#
#167
b10010011 (
1#
#168
0#
#169
b10010010 (
1#
#170
0#
#171
b10010001 (
1#
#172
0#
#173
b10010000 (
1#
#174
0#
#175
b10001111 (
1#
#176
0#
#177
b10001110 (
1#
#178
0#
#179
b10001101 (
1#
#180
0#
#181
b10001100 (
1#
#182
0#
#183
b10001011 (
1#
#184
0#
#185
b10001010 (
1#
#186
0#
#187
b10001001 (
1#
#188
0#
#189
b10001000 (
1#
#190
0#
#191
b10000111 (
1#
#192
0#
#193
b10000110 (
1#
#194
0#
#195
b10000101 (
1#
#196
0#
#197
b10000100 (
1#
#198
0#
#199
b10000011 (
1#
#200
0#
#201
b10000010 (
1#
#202
0#
#203
b10000001 (
1#
#204
0#
#205
b10000000 (
1#
#206
0#
#207
b1111111 (
1#
#208
0#
#209
b1111110 (
1#
#210
0#
#211
b1111101 (
1#
#212
0#
#213
b1111100 (
1#
#214
0#
#215
b1111011 (
1#
#216
0#
#217
b1111010 (
1#
#218
0#
#219
b1111001 (
1#
#220
0#
#221
b1111000 (
1#
#222
0#
#223
b1110111 (
1#
#224
0#
#225
b1110110 (
1#
#226
0#
#227
b1110101 (
1#
#228
0#
#229
b1110100 (
1#
#230
0#
#231
b1110011 (
1#
#232
0#
#233
b1110010 (
1#
#234
0#
#235
b1110001 (
1#
#236
0#
#237
b1110000 (
1#
#238
0#
#239
b1101111 (
1#
#240
0#
#241
b1101110 (
1#
#242
0#
#243
b1101101 (
1#
#244
0#
#245
b1101100 (
1#
#246
0#
#247
b1101011 (
1#
#248
0#
#249
b1101010 (
1#
#250
0#
#251
b1101001 (
1#
#252
0#
#253
b1101000 (
1#
#254
0#
#255
b1100111 (
1#
#256
0#
#257
b1100110 (
1#
#258
0#
#259
b1100101 (
1#
#260
0#
#261
b1100100 (
1#
#262
0#
#263
b1100011 (
1#
#264
0#
#265
b1100010 (
1#
#266
0#
#267
b1100001 (
1#
#268
0#
#269
b1100000 (
1#
#270
0#
#271
b1011111 (
1#
#272
0#
#273
b1011110 (
1#
#274
0#
#275
b1011101 (
1#
#276
0#
#277
b1011100 (
1#
#278
0#
#279
b1011011 (
1#
#280
0#
#281
b1011010 (
1#
#282
0#
#283
b1011001 (
1#
#284
0#
#285
b1011000 (
1#
#286
0#
#287
b1010111 (
1#
#288
0#
#289
b1010110 (
1#
#290
0#
#291
b1010101 (
1#
#292
0#
#293
b1010100 (
1#
#294
0#
#295
b1010011 (
1#
#296
0#
#297
b1010010 (
1#
#298
0#
#299
b1010001 (
1#
#300
0#
#301
b1010000 (
1#
#302
0#
#303
b1001111 (
1#
#304
0#
#305
b1001110 (
1#
#306
0#
#307
b1001101 (
1#
#308
0#
#309
b1001100 (
1#
#310
0#
#311
b1001011 (
1#
#312
0#
#313
b1001010 (
1#
#314
0#
#315
b1001001 (
1#
#316
0#
#317
b1001000 (
1#
#318
0#
#319
b1000111 (
1#
#320
0#
#321
b1000110 (
1#
#322
0#
#323
b1000101 (
1#
#324
0#
#325
b1000100 (
1#
#326
0#
#327
b1000011 (
1#
#328
0#
#329
b1000010 (
1#
#330
0#
#331
b1000001 (
1#
#332
0#
#333
b1000000 (
1#
#334
0#
#335
b111111 (
1#
#336
0#
#337
b111110 (
1#
#338
0#
#339
b111101 (
1#
#340
0#
#341
b111100 (
1#
#342
0#
#343
b111011 (
1#
#344
0#
#345
b111010 (
1#
#346
0#
#347
b111001 (
1#
#348
0#
#349
b111000 (
1#
#350
0#
#351
b110111 (
1#
#352
0#
#353
b110110 (
1#
#354
0#
#355
b110101 (
1#
#356
0#
#357
b110100 (
1#
#358
0#
#359
b110011 (
1#
#360
0#
#361
b110010 (
1#
#362
0#
#363
b110001 (
1#
#364
0#
#365
b110000 (
1#
#366
0#
#367
b101111 (
1#
#368
0#
#369
b101110 (
1#
#370
0#
#371
b101101 (
1#
#372
0#
#373
b101100 (
1#
#374
0#
#375
b101011 (
1#
#376
0#
#377
b101010 (
1#
#378
0#
#379
b101001 (
1#
#380
0#
#381
b101000 (
1#
#382
0#
#383
b100111 (
1#
#384
0#
#385
b100110 (
1#
#386
0#
#387
b100101 (
1#
#388
0#
#389
b100100 (
1#
#390
0#
#391
b100011 (
1#
#392
0#
#393
b100010 (
1#
#394
0#
#395
b100001 (
1#
#396
0#
#397
b100000 (
1#
#398
0#
#399
b11111 (
1#
#400
0#
#401
b11110 (
1#
#402
0#
#403
b11101 (
1#
#404
0#
#405
b11100 (
1#
#406
0#
#407
b11011 (
1#
#408
0#
#409
b11010 (
1#
#410
0#
#411
b11001 (
1#
#412
0#
#413
b11000 (
1#
#414
0#
#415
b10111 (
1#
#416
0#
#417
b10110 (
1#
#418
0#
#419
b10101 (
1#
#420
0#
#421
b10100 (
1#
#422
0#
#423
b10011 (
1#
#424
0#
#425
b10010 (
1#
#426
0#
#427
b10001 (
1#
#428
0#
#429
b10000 (
1#
#430
0#
#431
b1111 (
1#
#432
0#
#433
b1110 (
1#
#434
0#
#435
b1101 (
1#
#436
0#
#437
b1100 (
1#
#438
0#
#439
b1011 (
1#
#440
0#
#441
b1010 (
1#
#442
0#
#443
b1001 (
1#
#444
0#
#445
b1000 (
1#
#446
0#
#447
b111 (
1#
#448
0#
#449
b110 (
1#
#450
0#
#451
b101 (
1#
#452
0#
#453
b100 (
1#
#454
0#
#455
b11 (
1#
#456
0#
#457
b10 (
1#
#458
0#
#459
b1 (
1#
#460
0#
#461
1!
b0 (
1#
#462
0#
#463
0!
b10110101 (
1#
#464
0#
#465
b10110100 (
1#
#466
0#
#467
b10110011 (
1#
#468
0#
#469
b10110010 (
1#
#470
0#
#471
b10110001 (
1#
#472
0#
#473
b10110000 (
1#
#474
0#
#475
b10101111 (
1#
#476
0#
#477
b10101110 (
1#
#478
0#
#479
b10101101 (
1#
#480
0#
#481
b10101100 (
1#
#482
0#
#483
b10101011 (
1#
#484
0#
#485
b10101010 (
1#
#486
0#
#487
b10101001 (
1#
#488
0#
#489
b10101000 (
1#
#490
0#
#491
b10100111 (
1#
#492
0#
#493
b10100110 (
1#
#494
0#
#495
b10100101 (
1#
#496
0#
#497
b10100100 (
1#
#498
0#
#499
b10100011 (
1#
#500
0#
#501
b10100010 (
1#
#502
0#
#503
b10100001 (
1#
#504
0#
#505
b10100000 (
1#
#506
0#
#507
b10011111 (
1#
#508
0#
#509
b10011110 (
1#
#510
0#
#511
b10011101 (
1#
#512
0#
#513
b10011100 (
1#
#514
0#
#515
b10011011 (
1#
#516
0#
#517
b10011010 (
1#
#518
0#
#519
b10011001 (
1#
#520
0#
#521
b10011000 (
1#
#522
0#
#523
b10010111 (
1#
#524
0#
#525
b10010110 (
1#
#526
0#
#527
b10010101 (
1#
#528
0#
#529
b10010100 (
1#
#530
0#
#531
b10010011 (
1#
#532
0#
#533
b10010010 (
1#
#534
0#
#535
b10010001 (
1#
#536
0#
#537
b10010000 (
1#
#538
0#
#539
b10001111 (
1#
#540
0#
#541
b10001110 (
1#
#542
0#
#543
b10001101 (
1#
#544
0#
#545
b10001100 (
1#
#546
0#
#547
b10001011 (
1#
#548
0#
#549
b10001010 (
1#
#550
0#
#551
b10001001 (
1#
#552
0#
#553
b10001000 (
1#
#554
0#
#555
b10000111 (
1#
#556
0#
#557
b10000110 (
1#
#558
0#
#559
b10000101 (
1#
#560
0#
#561
b10000100 (
1#
#562
0#
#563
b10000011 (
1#
#564
0#
#565
b10000010 (
1#
#566
0#
#567
b10000001 (
1#
#568
0#
#569
b10000000 (
1#
#570
0#
#571
b1111111 (
1#
#572
0#
#573
b1111110 (
1#
#574
0#
#575
b1111101 (
1#
#576
0#
#577
b1111100 (
1#
#578
0#
#579
b1111011 (
1#
#580
0#
#581
b1111010 (
1#
#582
0#
#583
b1111001 (
1#
#584
0#
#585
b1111000 (
1#
#586
0#
#587
b1110111 (
1#
#588
0#
#589
b1110110 (
1#
#590
0#
#591
b1110101 (
1#
#592
0#
#593
b1110100 (
1#
#594
0#
#595
b1110011 (
1#
#596
0#
#597
b1110010 (
1#
#598
0#
#599
b1110001 (
1#
#600
0#
#601
b1110000 (
1#
#602
0#
#603
b1101111 (
1#
#604
0#
#605
b1101110 (
1#
#606
0#
#607
b1101101 (
1#
#608
0#
#609
b1101100 (
1#
#610
0#
#611
b1101011 (
1#
#612
0#
#613
b1101010 (
1#
#614
0#
#615
b1101001 (
1#
#616
0#
#617
b1101000 (
1#
#618
0#
#619
b1100111 (
1#
#620
0#
#621
b1100110 (
1#
#622
0#
#623
b1100101 (
1#
#624
0#
#625
b1100100 (
1#
#626
0#
#627
b1100011 (
1#
#628
0#
#629
b1100010 (
1#
#630
0#
#631
b1100001 (
1#
#632
0#
#633
b1100000 (
1#
#634
0#
#635
b1011111 (
1#
#636
0#
#637
b1011110 (
1#
#638
0#
#639
b1011101 (
1#
#640
0#
#641
b1011100 (
1#
#642
0#
#643
b1011011 (
1#
#644
0#
#645
b1011010 (
1#
#646
0#
#647
b1011001 (
1#
#648
0#
#649
b1011000 (
1#
#650
0#
#651
b1010111 (
1#
#652
0#
#653
b1010110 (
1#
#654
0#
#655
b1010101 (
1#
#656
0#
#657
b1010100 (
1#
#658
0#
#659
b1010011 (
1#
#660
0#
#661
b1010010 (
1#
#662
0#
#663
b1010001 (
1#
#664
0#
#665
b1010000 (
1#
#666
0#
#667
b1001111 (
1#
#668
0#
#669
b1001110 (
1#
#670
0#
#671
b1001101 (
1#
#672
0#
#673
b1001100 (
1#
#674
0#
#675
b1001011 (
1#
#676
0#
#677
b1001010 (
1#
#678
0#
#679
b1001001 (
1#
#680
0#
#681
b1001000 (
1#
#682
0#
#683
b1000111 (
1#
#684
0#
#685
b1000110 (
1#
#686
0#
#687
b1000101 (
1#
#688
0#
#689
b1000100 (
1#
#690
0#
#691
b1000011 (
1#
#692
0#
#693
b1000010 (
1#
#694
0#
#695
b1000001 (
1#
#696
0#
#697
b1000000 (
1#
#698
0#
#699
b111111 (
1#
#700
0#
#701
b111110 (
1#
#702
0#
#703
b111101 (
1#
#704
0#
#705
b111100 (
1#
#706
0#
#707
b111011 (
1#
#708
0#
#709
b111010 (
1#
#710
0#
#711
b111001 (
1#
#712
0#
#713
b111000 (
1#
#714
0#
#715
b110111 (
1#
#716
0#
#717
b110110 (
1#
#718
0#
#719
b110101 (
1#
#720
0#
#721
b110100 (
1#
#722
0#
#723
b110011 (
1#
#724
0#
#725
b110010 (
1#
#726
0#
#727
b110001 (
1#
#728
0#
#729
b110000 (
1#
#730
0#
#731
b101111 (
1#
#732
0#
#733
b101110 (
1#
#734
0#
#735
b101101 (
1#
#736
0#
#737
b101100 (
1#
#738
0#
#739
b101011 (
1#
#740
0#
#741
b101010 (
1#
#742
0#
#743
b101001 (
1#
#744
0#
#745
b101000 (
1#
#746
0#
#747
b100111 (
1#
#748
0#
#749
b100110 (
1#
#750
0#
#751
b100101 (
1#
#752
0#
#753
b100100 (
1#
#754
0#
#755
b100011 (
1#
#756
0#
#757
b100010 (
1#
#758
0#
#759
b100001 (
1#
#760
0#
#761
b100000 (
1#
#762
0#
#763
b11111 (
1#
#764
0#
#765
b11110 (
1#
#766
0#
#767
b11101 (
1#
#768
0#
#769
b11100 (
1#
#770
0#
#771
b11011 (
1#
#772
0#
#773
b11010 (
1#
#774
0#
#775
b11001 (
1#
#776
0#
#777
b11000 (
1#
#778
0#
#779
b10111 (
1#
#780
0#
#781
b10110 (
1#
#782
0#
#783
b10101 (
1#
#784
0#
#785
b10100 (
1#
#786
0#
#787
b10011 (
1#
#788
0#
#789
b10010 (
1#
#790
0#
#791
b10001 (
1#
#792
0#
#793
b10000 (
1#
#794
0#
#795
b1111 (
1#
#796
0#
#797
b1110 (
1#
#798
0#
#799
b1101 (
1#
#800
0#
#801
b1100 (
1#
#802
0#
#803
b1011 (
1#
#804
0#
#805
b1010 (
1#
#806
0#
#807
b1001 (
1#
#808
0#
#809
b1000 (
1#
#810
0#
#811
b111 (
1#
#812
0#
#813
b110 (
1#
#814
0#
#815
b101 (
1#
#816
0#
#817
b100 (
1#
#818
0#
#819
b11 (
1#
#820
0#
#821
b10 (
1#
#822
0#
#823
b1 (
1#
#824
0#
#825
1!
b0 (
1#
#826
0#
#827
0!
b10110101 (
1#
#828
0#
#829
b10110100 (
1#
#830
0#
#831
b10110011 (
1#
#832
0#
#833
b10110010 (
1#
#834
0#
#835
b10110001 (
1#
#836
0#
#837
b10110000 (
1#
#838
0#
#839
b10101111 (
1#
#840
0#
#841
b10101110 (
1#
#842
0#
#843
b10101101 (
1#
#844
0#
#845
b10101100 (
1#
#846
0#
#847
b10101011 (
1#
#848
0#
#849
b10101010 (
1#
#850
0#
#851
b10101001 (
1#
#852
0#
#853
b10101000 (
1#
#854
0#
#855
b10100111 (
1#
#856
0#
#857
b10100110 (
1#
#858
0#
#859
b10100101 (
1#
#860
0#
#861
b10100100 (
1#
#862
0#
#863
b10100011 (
1#
#864
0#
#865
b10100010 (
1#
#866
0#
#867
b10100001 (
1#
#868
0#
#869
b10100000 (
1#
#870
0#
#871
b10011111 (
1#
#872
0#
#873
b10011110 (
1#
#874
0#
#875
b10011101 (
1#
#876
0#
#877
b10011100 (
1#
#878
0#
#879
b10011011 (
1#
#880
0#
#881
b10011010 (
1#
#882
0#
#883
b10011001 (
1#
#884
0#
#885
b10011000 (
1#
#886
0#
#887
b10010111 (
1#
#888
0#
#889
b10010110 (
1#
#890
0#
#891
b10010101 (
1#
#892
0#
#893
b10010100 (
1#
#894
0#
#895
b10010011 (
1#
#896
0#
#897
b10010010 (
1#
#898
0#
#899
b10010001 (
1#
#900
0#
#901
b10010000 (
1#
#902
0#
#903
b10001111 (
1#
#904
0#
#905
b10001110 (
1#
#906
0#
#907
b10001101 (
1#
#908
0#
#909
b10001100 (
1#
#910
0#
#911
b10001011 (
1#
#912
0#
#913
b10001010 (
1#
#914
0#
#915
b10001001 (
1#
#916
0#
#917
b10001000 (
1#
#918
0#
#919
b10000111 (
1#
#920
0#
#921
b10000110 (
1#
#922
0#
#923
b10000101 (
1#
#924
0#
#925
b10000100 (
1#
#926
0#
#927
b10000011 (
1#
#928
0#
#929
b10000010 (
1#
#930
0#
#931
b10000001 (
1#
#932
0#
#933
b10000000 (
1#
#934
0#
#935
b1111111 (
1#
#936
0#
#937
b1111110 (
1#
#938
0#
#939
b1111101 (
1#
#940
0#
#941
b1111100 (
1#
#942
0#
#943
b1111011 (
1#
#944
0#
#945
b1111010 (
1#
#946
0#
#947
b1111001 (
1#
#948
0#
#949
b1111000 (
1#
#950
0#
#951
b1110111 (
1#
#952
0#
#953
b1110110 (
1#
#954
0#
#955
b1110101 (
1#
#956
0#
#957
b1110100 (
1#
#958
0#
#959
b1110011 (
1#
#960
0#
#961
b1110010 (
1#
#962
0#
#963
b1110001 (
1#
#964
0#
#965
b1110000 (
1#
#966
0#
#967
b1101111 (
1#
#968
0#
#969
b1101110 (
1#
#970
0#
#971
b1101101 (
1#
#972
0#
#973
b1101100 (
1#
#974
0#
#975
b1101011 (
1#
#976
0#
#977
b1101010 (
1#
#978
0#
#979
b1101001 (
1#
#980
0#
#981
b1101000 (
1#
#982
0#
#983
b1100111 (
1#
#984
0#
#985
b1100110 (
1#
#986
0#
#987
b1100101 (
1#
#988
0#
#989
b1100100 (
1#
#990
0#
#991
b1100011 (
1#
#992
0#
#993
b1100010 (
1#
#994
0#
#995
b1100001 (
1#
#996
0#
#997
b1100000 (
1#
#998
0#
#999
b1011111 (
1#
#1000
0#
#1001
b1011110 (
1#
#1002
0#
#1003
b1011101 (
1#
#1004
0#
#1005
b1011100 (
1#
#1006
0#
#1007
b1011011 (
1#
#1008
0#
#1009
b1011010 (
1#
#1010
0#
#1011
b1011001 (
1#
#1012
0#
#1013
b1011000 (
1#
#1014
0#
#1015
b1010111 (
1#
#1016
0#
#1017
b1010110 (
1#
#1018
0#
#1019
b1010101 (
1#
#1020
0#
#1021
b1010100 (
1#
#1022
0#
#1023
b1010011 (
1#
#1024
0#
#1025
b1010010 (
1#
#1026
0#
#1027
b1010001 (
1#
#1028
0#
#1029
b1010000 (
1#
#1030
0#
#1031
b1001111 (
1#
#1032
0#
#1033
b1001110 (
1#
#1034
0#
#1035
b1001101 (
1#
#1036
0#
#1037
b1001100 (
1#
#1038
0#
#1039
b1001011 (
1#
#1040
0#
#1041
b1001010 (
1#
#1042
0#
#1043
b1001001 (
1#
#1044
0#
#1045
b1001000 (
1#
#1046
0#
#1047
b1000111 (
1#
#1048
0#
#1049
b1000110 (
1#
#1050
0#
#1051
b1000101 (
1#
#1052
0#
#1053
b1000100 (
1#
#1054
0#
#1055
b1000011 (
1#
#1056
0#
#1057
b1000010 (
1#
#1058
0#
#1059
b1000001 (
1#
#1060
0#
#1061
b1000000 (
1#
#1062
0#
#1063
b111111 (
1#
#1064
0#
#1065
b111110 (
1#
#1066
0#
#1067
b111101 (
1#
#1068
0#
#1069
b111100 (
1#
#1070
0#
#1071
b111011 (
1#
#1072
0#
#1073
b111010 (
1#
#1074
0#
#1075
b111001 (
1#
#1076
0#
#1077
b111000 (
1#
#1078
0#
#1079
b110111 (
1#
#1080
0#
#1081
b110110 (
1#
#1082
0#
#1083
b110101 (
1#
#1084
0#
#1085
b110100 (
1#
#1086
0#
#1087
b110011 (
1#
#1088
0#
#1089
b110010 (
1#
#1090
0#
#1091
b110001 (
1#
#1092
0#
#1093
b110000 (
1#
#1094
0#
#1095
b101111 (
1#
#1096
0#
#1097
b101110 (
1#
#1098
0#
#1099
b101101 (
1#
#1100
0#
1%
#1101
b10110101 (
1#
#1102
0#
#1103
1#
#1104
0#
#1105
b10110100 (
1#
0%
#1106
0#
#1107
b10110011 (
1#
#1108
0#
#1109
b10110010 (
1#
#1110
0#
#1111
b10110001 (
1#
#1112
0#
#1113
b10110000 (
1#
#1114
0#
#1115
b10101111 (
1#
#1116
0#
#1117
b10101110 (
1#
#1118
0#
#1119
b10101101 (
1#
#1120
0#
#1121
b10101100 (
1#
#1122
0#
#1123
b10101011 (
1#
#1124
0#
#1125
b10101010 (
1#
#1126
0#
#1127
b10101001 (
1#
#1128
0#
#1129
b10101000 (
1#
#1130
0#
#1131
b10100111 (
1#
#1132
0#
#1133
b10100110 (
1#
#1134
0#
#1135
b10100101 (
1#
#1136
0#
#1137
b10100100 (
1#
#1138
0#
#1139
b10100011 (
1#
#1140
0#
#1141
b10100010 (
1#
#1142
0#
#1143
b10100001 (
1#
#1144
0#
#1145
b10100000 (
1#
#1146
0#
#1147
b10011111 (
1#
#1148
0#
#1149
b10011110 (
1#
#1150
0#
#1151
b10011101 (
1#
#1152
0#
#1153
b10011100 (
1#
#1154
0#
#1155
b10011011 (
1#
#1156
0#
#1157
b10011010 (
1#
#1158
0#
#1159
b10011001 (
1#
#1160
0#
#1161
b10011000 (
1#
#1162
0#
#1163
b10010111 (
1#
#1164
0#
#1165
b10010110 (
1#
#1166
0#
#1167
b10010101 (
1#
#1168
0#
#1169
b10010100 (
1#
#1170
0#
#1171
b10010011 (
1#
#1172
0#
#1173
b10010010 (
1#
#1174
0#
#1175
b10010001 (
1#
#1176
0#
#1177
b10010000 (
1#
#1178
0#
#1179
b10001111 (
1#
#1180
0#
#1181
b10001110 (
1#
#1182
0#
#1183
b10001101 (
1#
#1184
0#
#1185
b10001100 (
1#
#1186
0#
#1187
b10001011 (
1#
#1188
0#
#1189
b10001010 (
1#
#1190
0#
#1191
b10001001 (
1#
#1192
0#
#1193
b10001000 (
1#
#1194
0#
#1195
b10000111 (
1#
#1196
0#
#1197
b10000110 (
1#
#1198
0#
#1199
b10000101 (
1#
#1200
0#
#1201
b10000100 (
1#
#1202
0#
#1203
b10000011 (
1#
#1204
0#
#1205
b10000010 (
1#
#1206
0#
#1207
b10000001 (
1#
#1208
0#
#1209
b10000000 (
1#
#1210
0#
#1211
b1111111 (
1#
#1212
0#
#1213
b1111110 (
1#
#1214
0#
#1215
b1111101 (
1#
#1216
0#
#1217
b1111100 (
1#
#1218
0#
#1219
b1111011 (
1#
#1220
0#
#1221
b1111010 (
1#
#1222
0#
#1223
b1111001 (
1#
#1224
0#
#1225
b1111000 (
1#
#1226
0#
#1227
b1110111 (
1#
#1228
0#
#1229
b1110110 (
1#
#1230
0#
#1231
b1110101 (
1#
#1232
0#
#1233
b1110100 (
1#
#1234
0#
#1235
b1110011 (
1#
#1236
0#
#1237
b1110010 (
1#
#1238
0#
#1239
b1110001 (
1#
#1240
0#
#1241
b1110000 (
1#
#1242
0#
#1243
b1101111 (
1#
#1244
0#
#1245
b1101110 (
1#
#1246
0#
#1247
b1101101 (
1#
#1248
0#
#1249
b1101100 (
1#
#1250
0#
#1251
b1101011 (
1#
#1252
0#
#1253
b1101010 (
1#
#1254
0#
#1255
b1101001 (
1#
#1256
0#
#1257
b1101000 (
1#
#1258
0#
#1259
b1100111 (
1#
#1260
0#
#1261
b1100110 (
1#
#1262
0#
#1263
b1100101 (
1#
#1264
0#
#1265
b1100100 (
1#
#1266
0#
#1267
b1100011 (
1#
#1268
0#
#1269
b1100010 (
1#
#1270
0#
#1271
b1100001 (
1#
#1272
0#
#1273
b1100000 (
1#
#1274
0#
#1275
b1011111 (
1#
#1276
0#
#1277
b1011110 (
1#
#1278
0#
#1279
b1011101 (
1#
#1280
0#
#1281
b1011100 (
1#
#1282
0#
#1283
b1011011 (
1#
#1284
0#
#1285
b1011010 (
1#
#1286
0#
#1287
b1011001 (
1#
#1288
0#
#1289
b1011000 (
1#
#1290
0#
#1291
b1010111 (
1#
#1292
0#
#1293
b1010110 (
1#
#1294
0#
#1295
b1010101 (
1#
#1296
0#
#1297
b1010100 (
1#
#1298
0#
#1299
b1010011 (
1#
#1300
0#
#1301
b1010010 (
1#
#1302
0#
#1303
b1010001 (
1#
#1304
0#
#1305
b1010000 (
1#
#1306
0#
#1307
b1001111 (
1#
#1308
0#
#1309
b1001110 (
1#
#1310
0#
#1311
b1001101 (
1#
#1312
0#
#1313
b1001100 (
1#
#1314
0#
#1315
b1001011 (
1#
#1316
0#
#1317
b1001010 (
1#
#1318
0#
#1319
b1001001 (
1#
#1320
0#
#1321
b1001000 (
1#
#1322
0#
#1323
b1000111 (
1#
#1324
0#
#1325
b1000110 (
1#
#1326
0#
#1327
b1000101 (
1#
#1328
0#
#1329
b1000100 (
1#
#1330
0#
#1331
b1000011 (
1#
#1332
0#
#1333
b1000010 (
1#
#1334
0#
#1335
b1000001 (
1#
#1336
0#
#1337
b1000000 (
1#
#1338
0#
#1339
b111111 (
1#
#1340
0#
#1341
b111110 (
1#
#1342
0#
#1343
b111101 (
1#
#1344
0#
#1345
b111100 (
1#
#1346
0#
#1347
b111011 (
1#
#1348
0#
#1349
b111010 (
1#
#1350
0#
#1351
b111001 (
1#
#1352
0#
#1353
b111000 (
1#
#1354
0#
#1355
b110111 (
1#
#1356
0#
#1357
b110110 (
1#
#1358
0#
#1359
b110101 (
1#
#1360
0#
#1361
b110100 (
1#
#1362
0#
#1363
b110011 (
1#
#1364
0#
#1365
b110010 (
1#
#1366
0#
#1367
b110001 (
1#
#1368
0#
#1369
b110000 (
1#
#1370
0#
#1371
b101111 (
1#
#1372
0#
#1373
b101110 (
1#
#1374
0#
#1375
b101101 (
1#
#1376
0#
#1377
b101100 (
1#
#1378
0#
#1379
b101011 (
1#
#1380
0#
#1381
b101010 (
1#
#1382
0#
#1383
b101001 (
1#
#1384
0#
#1385
b101000 (
1#
#1386
0#
#1387
b100111 (
1#
#1388
0#
#1389
b100110 (
1#
#1390
0#
#1391
b100101 (
1#
#1392
0#
#1393
b100100 (
1#
#1394
0#
#1395
b100011 (
1#
#1396
0#
#1397
b100010 (
1#
#1398
0#
#1399
b100001 (
1#
#1400
0#
#1401
b100000 (
1#
#1402
0#
#1403
b11111 (
1#
#1404
0#
#1405
b11110 (
1#
#1406
0#
#1407
b11101 (
1#
#1408
0#
#1409
b11100 (
1#
#1410
0#
#1411
b11011 (
1#
#1412
0#
#1413
b11010 (
1#
#1414
0#
#1415
b11001 (
1#
#1416
0#
#1417
b11000 (
1#
#1418
0#
#1419
b10111 (
1#
#1420
0#
#1421
b10110 (
1#
#1422
0#
#1423
b10101 (
1#
#1424
0#
#1425
b10100 (
1#
#1426
0#
#1427
b10011 (
1#
#1428
0#
#1429
b10010 (
1#
#1430
0#
#1431
b10001 (
1#
#1432
0#
#1433
b10000 (
1#
#1434
0#
#1435
b1111 (
1#
#1436
0#
#1437
b1110 (
1#
#1438
0#
#1439
b1101 (
1#
#1440
0#
#1441
b1100 (
1#
#1442
0#
#1443
b1011 (
1#
#1444
0#
#1445
b1010 (
1#
#1446
0#
#1447
b1001 (
1#
#1448
0#
#1449
b1000 (
1#
#1450
0#
#1451
b111 (
1#
#1452
0#
#1453
b110 (
1#
#1454
0#
#1455
b101 (
1#
#1456
0#
#1457
b100 (
1#
#1458
0#
#1459
b11 (
1#
#1460
0#
#1461
b10 (
1#
#1462
0#
#1463
b1 (
1#
#1464
0#
#1465
1!
b0 (
1#
#1466
0#
#1467
0!
b10110101 (
1#
#1468
0#
#1469
b10110100 (
1#
#1470
0#
#1471
b10110011 (
1#
#1472
0#
#1473
b10110010 (
1#
#1474
0#
#1475
b10110001 (
1#
#1476
0#
#1477
b10110000 (
1#
#1478
0#
#1479
b10101111 (
1#
#1480
0#
#1481
b10101110 (
1#
#1482
0#
