verilog_files/Lab_2_Code/lab2_beltwarn.v
module beltwarn_s(
	input wire K, P, S,
	output wire W );

wire N1, N2;

not Inv_1 (N2, S);
and And2_1(N1, K, P);
and And2_2(W, N1, N2);

endmodule

module beltwarn_b(
	input wire K, P, S,
	output reg W );


always@(K,P,S) begin
	W <= K & P & !S;
end

endmodule

verilog_files/Lab_2_Code/lab2_beltwarn_tb.v
`timescale 1ns / 1ns
`include "lab2_beltwarn.v"
module lab2_beltwarn_tb;

reg K; reg P; reg S;
wire W;

beltwarn_s uut(.K(K),.P(P), .S(S), .W(W));
initial begin
	K = 0; P = 0; S = 0;
	#20;
	
	K = 0; P = 0; S = 1;
	#20;
	
	K = 0; P = 1; S = 0;
	#20;
	
	K = 0; P = 1; S = 1;
	#20;
	
	K = 1; P = 0; S = 0;
	#20;
	
	K = 1; P = 0; S = 1;
	#20;
	
	K = 1; P = 1; S = 0;
	#20;
	
	K = 1; P = 1; S = 1;
	#20;

end

beltwarn_b uut2(.K(K),.P(P), .S(S), .W(W));
initial begin

	K = 0; P = 0; S = 0;
	#20;
	
	K = 0; P = 0; S = 1;
	#20;
	
	K = 0; P = 1; S = 0;
	#20;
	
	K = 0; P = 1; S = 1;
	#20;
	
	K = 1; P = 0; S = 0;
	#20;
	
	K = 1; P = 0; S = 1;
	#20;
	
	K = 1; P = 1; S = 0;
	#20;
	
	K = 1; P = 1; S = 1;
	#20;

end

endmodule

verilog_files/Lab_2_Code/lab2_beltwarn_tb.vcd
$date
	Tue Jun 29 14:47:16 2021
$end
$version
	Icarus Verilog
$end
$timescale
	1ns
$end
$scope module lab2_beltwarn_tb $end
$var wire 1 ! W $end
$var reg 1 " K $end
$var reg 1 # P $end
$var reg 1 $ S $end
$scope module uut $end
$var wire 1 " K $end
$var wire 1 % N1 $end
$var wire 1 & N2 $end
$var wire 1 # P $end
$var wire 1 $ S $end
$var wire 1 ! W $end
$upscope $end
$scope module uut2 $end
$var wire 1 " K $end
$var wire 1 # P $end
$var wire 1 $ S $end
$var reg 1 ' W $end
$upscope $end
$upscope $end
$enddefinitions $end
#0
$dumpvars
0'
1&
0%
0$
0#
0"
0!
$end
#20
0&
1$
#40
1&
0$
1#
#60
0&
1$
#80
1&
0$
0#
1"
#100
0&
1$
#120
1'
1!
1&
1%
0$
1#
#140
0'
0!
0&
1$
