verilog_files/Lab_3_Code/lab3_bcd.v
module bcd_to_7led_b ( 
 input wire sw0 , // Switches 
 input wire sw1 , 
 input wire sw2 , 
 input wire sw3 , 
 output reg a , // LED segments 
 output reg b , 
 output reg c , 
 output reg d , 
 output reg e , 
 output reg f , 
 output reg g , 
 output reg an0, // LED display control 
 output reg an1, 
 output reg an2, 
 output reg an3 
 ); 
// Internal wire 
wire [3:0] bundle ; 
assign bundle = {sw3,sw2,sw1,sw0 } ; 
always @(*) begin 
 // Setting the ANs signals 
 an0 = 1'b1; 
 an1 = 1'b1; 
 an2 = 1'b1; 
 an3 = 1'b0; // Display in the module AN3 Lab3 “ Combinatorial Logic ” 
 // Setting the segments signals 
 a = 1'b1 ; 
 b = 1'b1 ; 
 c = 1'b1 ; 
 d = 1'b1 ; 
 e = 1'b1 ; 
 f = 1'b1 ; 
 g = 1'b1 ; 
 
 case ( bundle ) 
 4'b0000 : begin // 0 
 a = 1'b0 ; 
 b = 1'b0 ; 
 c = 1'b0 ; 
 d = 1'b0 ; 
 e = 1'b0 ; 
 f = 1'b0 ; 
 // g = 1'b1 ; 
 end 
 
 4'b0001 : begin // 1 
 b = 1'b0 ; 
 c = 1'b0 ; 
 end 
 
  4'b0010 : begin // 2 
 a = 1'b0 ; 
 b = 1'b0 ; 
 d = 1'b0 ; 
 e = 1'b0 ; 
 g = 1'b0;
 end 
 
  4'b0011 : begin // 3 
 a = 1'b0 ; 
 b = 1'b0 ; 
 c = 1'b0 ; 
 d = 1'b0 ; 
 g = 1'b0;
 end 
 
  4'b0100 : begin // 4 
 b = 1'b0 ; 
 c = 1'b0 ; 
 f = 1'b0 ; 
 g = 1'b0;
 end 
 
  4'b0101 : begin // 5 
 a = 1'b0 ; 
 c = 1'b0 ; 
 d = 1'b0 ; 
 f = 1'b0 ; 
 g = 1'b0;
 end 
 
  4'b0110 : begin // 6 
 a = 1'b0 ; 
 c = 1'b0 ; 
 d = 1'b0 ; 
 e = 1'b0 ; 
 f = 1'b0 ; 
 g = 1'b0;
 end 
 
  4'b0111 : begin // 7 
 a = 1'b0 ; 
 b = 1'b0 ; 
 c = 1'b0 ; 
 end 
 
  4'b1000 : begin // 8 
 a = 1'b0 ; 
 b = 1'b0 ; 
 c = 1'b0 ; 
 d = 1'b0 ; 
 e = 1'b0 ; 
 f = 1'b0 ; 
 g = 1'b0;
 end 
 
  4'b1001 : begin // 9 
 a = 1'b0 ; 
 b = 1'b0 ; 
 c = 1'b0 ; 
 d = 1'b0 ; 
 f = 1'b0 ; 
 g = 1'b0;
 end 

 endcase 
 
 
end 
endmodule

verilog_files/Lab_3_Code/lab3_bcd_tb.v
`timescale 1ns / 1ns
`include "lab3_bcd.v"
module lab3_bcd_tb;
wire A; wire B;wire C;wire D;wire E;wire F;wire G; 
reg [3:0]S;
bcd_to_7led_b uut(.sw3(S[3]),.sw2(S[2]),.sw1(S[1]),.sw0(S[0]),.a(A),.b(B),.c(C),.d(D),.e(E),.f(F),.g(G));
initial begin
$dumpfile("lab3_bcd_tb.vcd");
$dumpvars(0,lab3_bcd_tb);
S=4'b0000;#20;
S=4'b0001;#20;
S=4'b0010;#20;
S=4'b0011;#20;
S=4'b0100;#20;
S=4'b0101;#20;
S=4'b0110;#20;
S=4'b0111;#20;
S=4'b1000;#20;
S=4'b1001;#20;
end
endmodule

verilog_files/Lab_3_Code/lab3_bcd_tb.vcd
$date
	Tue Jul 06 11:46:30 2021
$end
$version
	Icarus Verilog
$end
$timescale
	1ns
$end
$scope module lab3_bcd_tb $end
$var wire 1 ! G $end
$var wire 1 " F $end
$var wire 1 # E $end
$var wire 1 $ D $end
$var wire 1 % C $end
$var wire 1 & B $end
$var wire 1 ' A $end
$var reg 4 ( S [3:0] $end
$scope module uut $end
$var wire 1 ) sw0 $end
$var wire 1 * sw1 $end
$var wire 1 + sw2 $end
$var wire 1 , sw3 $end
$var wire 4 - bundle [3:0] $end
$var reg 1 ' a $end
$var reg 1 . an0 $end
$var reg 1 / an1 $end
$var reg 1 0 an2 $end
$var reg 1 1 an3 $end
$var reg 1 & b $end
$var reg 1 % c $end
$var reg 1 $ d $end
$var reg 1 # e $end
$var reg 1 " f $end
$var reg 1 ! g $end
$upscope $end
$upscope $end
$enddefinitions $end
#0
$dumpvars
01
10
1/
1.
b0 -
0,
0+
0*
0)
b0 (
0'
0&
0%
0$
0#
0"
1!
$end
#20
1"
1#
1$
0%
0&
1'
b1 -
1)
b1 (
#40
0!
0#
0$
0'
1%
0&
0)
b10 -
1*
b10 (
#60
0%
0!
1#
0$
0&
0'
b11 -
1)
b11 (
#80
0"
0!
1$
0%
0&
1'
0)
0*
b100 -
1+
b100 (
#100
0$
0'
0!
0"
0%
1&
b101 -
1)
b101 (
#120
0#
0!
0"
0$
0%
0'
0)
b110 -
1*
b110 (
#140
0&
1!
1"
1#
1$
0%
0'
b111 -
1)
b111 (
#160
0!
0"
0#
0$
0%
0&
0'
0)
0*
0+
b1000 -
1,
b1000 (
#180
0!
0"
1#
0$
0%
0&
0'
b1001 -
1)
b1001 (
