verilog_files/Lab_3_Code/lab3_comparator.v
module comp_str(
	input wire [3:0] A,
	input wire [3:0] B,
	output wire Q ) ;

wire t1, t2, t3, t4;

xor c1(t1, A[0], B[0]);
xor c2(t2, A[1], B[1]);
xor c3(t3, A[2], B[2]);
xor c4(t4, A[3], B[3]);
or c5(Q, t1, t2, t3, t4);
endmodule

module comp_b(
	input wire [3:0] A,
	input wire [3:0] B,
	output reg Q ) ;

reg t1, t2, t3, t4;

always @(*) begin

t1 = A[0] ^ B[0];
t2 = A[1] ^ B[1];
t3 = A[2] ^ B[2];
t4 = A[3] ^ B[3];
Q = t1 | t2 | t3 | t4;
end
endmodule


module comp_d(
	input wire [3:0] A,
	input wire [3:0] B,
	output wire Q ) ;

wire t1, t2, t3, t4;

assign t1 = A[0] ^ B[0];
assign t2 = A[1] ^ B[1];
assign t3 = A[2] ^ B[2];
assign t4 = A[3] ^ B[3];
assign Q = t1 | t2 | t3 | t4;
endmodule

verilog_files/Lab_3_Code/lab3_comparator_tb.v
`timescale 1ns / 1ns
`include "lab3_comparator.v"

module lab3_comp_s_tb;

reg [3:0] A;
reg [3:0] B;
wire Q;

comp_str uut(.A(A),.B(B), .Q(Q));
initial begin
	$dumpfile("lab3_comparator_tb.vcd");
	$dumpvars(0,lab3_comp_s_tb);
	
	//5 cases == 
	assign A[0] = 1; assign A[1] = 0; assign A[2] = 0; assign A[3] = 1;
	assign B[0] = 1; assign B[1] = 0; assign B[2] = 0; assign B[3] = 1;
	#10;
	
	assign A[0] = 1; assign A[1] = 1; assign A[2] = 1; assign A[3] = 0;
	assign B[0] = 1; assign B[1] = 1; assign B[2] = 1; assign B[3] = 0;
	#10;
	
	assign A[0] = 1; assign A[1] = 0; assign A[2] = 0; assign A[3] = 0;
	assign B[0] = 1; assign B[1] = 0; assign B[2] = 0; assign B[3] = 0;
	#10;
	
	assign A[0] = 0; assign A[1] = 0; assign A[2] = 0; assign A[3] = 0;
	assign B[0] = 0; assign B[1] = 0; assign B[2] = 0; assign B[3] = 0;
	#10;
	
	assign A[0] = 1; assign A[1] = 1; assign A[2] = 1; assign A[3] = 1;
	assign B[0] = 1; assign B[1] = 1; assign B[2] = 1; assign B[3] = 1;
	#10;
	
	//5 cases !=
	assign A[0] = 0; assign A[1] = 1; assign A[2] = 1; assign A[3] = 0;
	assign B[0] = 1; assign B[1] = 0; assign B[2] = 0; assign B[3] = 1;
	#10;
	
	assign A[0] = 1; assign A[1] = 0; assign A[2] = 0; assign A[3] = 1;
	assign B[0] = 0; assign B[1] = 1; assign B[2] = 1; assign B[3] = 0;
	#10;

	assign A[0] = 0; assign A[1] = 0; assign A[2] = 1; assign A[3] = 1;
	assign B[0] = 1; assign B[1] = 1; assign B[2] = 0; assign B[3] = 0;
	#10;
	
	assign A[0] = 1; assign A[1] = 1; assign A[2] = 0; assign A[3] = 0;
	assign B[0] = 0; assign B[1] = 0; assign B[2] = 1; assign B[3] = 1;
	#10;
	
	assign A[0] = 1; assign A[1] = 0; assign A[2] = 1; assign A[3] = 0;
	assign B[0] = 0; assign B[1] = 1; assign B[2] = 0; assign B[3] = 1;
	#10;
	
end
endmodule

module lab3_comp_b_tb;

reg [3:0] A;
reg [3:0] B;
wire Q;

comp_b uut(.A(A),.B(B), .Q(Q));
initial begin
	$dumpfile("lab3_comparator_tb.vcd");
	$dumpvars(0,lab3_comp_b_tb);
	
	//5 cases == 
	assign A[0] = 1; assign A[1] = 0; assign A[2] = 0; assign A[3] = 1;
	assign B[0] = 1; assign B[1] = 0; assign B[2] = 0; assign B[3] = 1;
	#10;
	
	assign A[0] = 1; assign A[1] = 1; assign A[2] = 1; assign A[3] = 0;
	assign B[0] = 1; assign B[1] = 1; assign B[2] = 1; assign B[3] = 0;
	#10;
	
	assign A[0] = 1; assign A[1] = 0; assign A[2] = 0; assign A[3] = 0;
	assign B[0] = 1; assign B[1] = 0; assign B[2] = 0; assign B[3] = 0;
	#10;
	
	assign A[0] = 0; assign A[1] = 0; assign A[2] = 0; assign A[3] = 0;
	assign B[0] = 0; assign B[1] = 0; assign B[2] = 0; assign B[3] = 0;
	#10;
	
	assign A[0] = 1; assign A[1] = 1; assign A[2] = 1; assign A[3] = 1;
	assign B[0] = 1; assign B[1] = 1; assign B[2] = 1; assign B[3] = 1;
	#10;
	
	//5 cases !=
	assign A[0] = 0; assign A[1] = 1; assign A[2] = 1; assign A[3] = 0;
	assign B[0] = 1; assign B[1] = 0; assign B[2] = 0; assign B[3] = 1;
	#10;
	
	assign A[0] = 1; assign A[1] = 0; assign A[2] = 0; assign A[3] = 1;
	assign B[0] = 0; assign B[1] = 1; assign B[2] = 1; assign B[3] = 0;
	#10;

	assign A[0] = 0; assign A[1] = 0; assign A[2] = 1; assign A[3] = 1;
	assign B[0] = 1; assign B[1] = 1; assign B[2] = 0; assign B[3] = 0;
	#10;
	
	assign A[0] = 1; assign A[1] = 1; assign A[2] = 0; assign A[3] = 0;
	assign B[0] = 0; assign B[1] = 0; assign B[2] = 1; assign B[3] = 1;
	#10;
	
	assign A[0] = 1; assign A[1] = 0; assign A[2] = 1; assign A[3] = 0;
	assign B[0] = 0; assign B[1] = 1; assign B[2] = 0; assign B[3] = 1;
	#10;
	
end
endmodule

module lab3_comp_d_tb;

reg [3:0] A;
reg [3:0] B;
wire Q;

comp_d uut(.A(A),.B(B), .Q(Q));
initial begin
	$dumpfile("lab3_comparator_tb.vcd");
	$dumpvars(0,lab3_comp_d_tb);
	
	//5 cases == 
	assign A[0] = 1; assign A[1] = 0; assign A[2] = 0; assign A[3] = 1;
	assign B[0] = 1; assign B[1] = 0; assign B[2] = 0; assign B[3] = 1;
	#10;
	
	assign A[0] = 1; assign A[1] = 1; assign A[2] = 1; assign A[3] = 0;
	assign B[0] = 1; assign B[1] = 1; assign B[2] = 1; assign B[3] = 0;
	#10;
	
	assign A[0] = 1; assign A[1] = 0; assign A[2] = 0; assign A[3] = 0;
	assign B[0] = 1; assign B[1] = 0; assign B[2] = 0; assign B[3] = 0;
	#10;
	
	assign A[0] = 0; assign A[1] = 0; assign A[2] = 0; assign A[3] = 0;
	assign B[0] = 0; assign B[1] = 0; assign B[2] = 0; assign B[3] = 0;
	#10;
	
	assign A[0] = 1; assign A[1] = 1; assign A[2] = 1; assign A[3] = 1;
	assign B[0] = 1; assign B[1] = 1; assign B[2] = 1; assign B[3] = 1;
	#10;
	
	//5 cases !=
	assign A[0] = 0; assign A[1] = 1; assign A[2] = 1; assign A[3] = 0;
	assign B[0] = 1; assign B[1] = 0; assign B[2] = 0; assign B[3] = 1;
	#10;
	
	assign A[0] = 1; assign A[1] = 0; assign A[2] = 0; assign A[3] = 1;
	assign B[0] = 0; assign B[1] = 1; assign B[2] = 1; assign B[3] = 0;
	#10;

	assign A[0] = 0; assign A[1] = 0; assign A[2] = 1; assign A[3] = 1;
	assign B[0] = 1; assign B[1] = 1; assign B[2] = 0; assign B[3] = 0;
	#10;
	
	assign A[0] = 1; assign A[1] = 1; assign A[2] = 0; assign A[3] = 0;
	assign B[0] = 0; assign B[1] = 0; assign B[2] = 1; assign B[3] = 1;
	#10;
	
	assign A[0] = 1; assign A[1] = 0; assign A[2] = 1; assign A[3] = 0;
	assign B[0] = 0; assign B[1] = 1; assign B[2] = 0; assign B[3] = 1;
	#10;
	
end
endmodule

verilog_files/Lab_3_Code/lab3_comparator_tb.vcd
$date
	Tue Jul 06 11:46:10 2021
$end
$version
	Icarus Verilog
$end
$timescale
	1ns
$end
$scope module lab3_comp_b_tb $end
$var wire 1 ! Q $end
$var reg 4 " A [3:0] $end
$var reg 4 # B [3:0] $end
$scope module uut $end
$var wire 4 $ A [3:0] $end
$var wire 4 % B [3:0] $end
$var reg 1 ! Q $end
$var reg 1 & t1 $end
$var reg 1 ' t2 $end
$var reg 1 ( t3 $end
$var reg 1 ) t4 $end
$upscope $end
$upscope $end
$scope module lab3_comp_d_tb $end
$var wire 1 * Q $end
$var reg 4 + A [3:0] $end
$var reg 4 , B [3:0] $end
$scope module uut $end
$var wire 4 - A [3:0] $end
$var wire 4 . B [3:0] $end
$var wire 1 * Q $end
$var wire 1 / t1 $end
$var wire 1 0 t2 $end
$var wire 1 1 t3 $end
$var wire 1 2 t4 $end
$upscope $end
$upscope $end
$scope module lab3_comp_s_tb $end
$var wire 1 3 Q $end
$var reg 4 4 A [3:0] $end
$var reg 4 5 B [3:0] $end
$scope module uut $end
$var wire 4 6 A [3:0] $end
$var wire 4 7 B [3:0] $end
$var wire 1 3 Q $end
$var wire 1 8 t1 $end
$var wire 1 9 t2 $end
$var wire 1 : t3 $end
$var wire 1 ; t4 $end
$upscope $end
$upscope $end
$enddefinitions $end
#0
$dumpvars
0;
0:
09
08
b1001 7
b1001 6
b1001 5
b1001 4
03
02
01
00
0/
b1001 .
b1001 -
b1001 ,
b1001 +
0*
0)
0(
0'
0&
b1001 %
b1001 $
b1001 #
b1001 "
0!
$end
#10
b111 5
b111 7
b111 4
b111 6
b111 ,
b111 .
b111 +
b111 -
b111 #
b111 %
b111 "
b111 $
#20
b1 5
b1 7
b1 4
b1 6
b1 ,
b1 .
b1 +
b1 -
b1 #
b1 %
b1 "
b1 $
#30
b0 5
b0 7
b0 4
b0 6
b0 ,
b0 .
b0 +
b0 -
b0 #
b0 %
b0 "
b0 $
#40
b1111 5
b1111 7
b1111 4
b1111 6
b1111 ,
b1111 .
b1111 +
b1111 -
b1111 #
b1111 %
b1111 "
b1111 $
#50
13
1*
1:
19
1;
18
11
10
12
1/
1!
1)
1(
1'
1&
b1001 5
b1001 7
b110 4
b110 6
b1001 ,
b1001 .
b110 +
b110 -
b1001 #
b1001 %
b110 "
b110 $
#60
b110 5
b110 7
b1001 4
b1001 6
b110 ,
b110 .
b1001 +
b1001 -
b110 #
b110 %
b1001 "
b1001 $
#70
b11 5
b11 7
b1100 4
b1100 6
b11 ,
b11 .
b1100 +
b1100 -
b11 #
b11 %
b1100 "
b1100 $
#80
b1100 5
b1100 7
b11 4
b11 6
b1100 ,
b1100 .
b11 +
b11 -
b1100 #
b1100 %
b11 "
b11 $
#90
b1010 5
b1010 7
b101 4
b101 6
b1010 ,
b1010 .
b101 +
b101 -
b1010 #
b1010 %
b101 "
b101 $
