verilog_files/Labtest/labtest.v
module Priority_Encoder4( 
 input wire [3:0] In,
 output wire [1:0] Out,
 output wire V
 ); 

//priority 3 -> 1 -> 0 -> 2
wire tempAnd;
and(tempAnd, !In[1], !In[0]); 
or c1(Out[1], tempAnd, In[3]);
or c2(Out[0], In[3], In[1]);
or c3(V, In[3], In[2], In[1], In[0]);


endmodule

verilog_files/hello/labtest_tb.v
`timescale 1ns/1ns
`include "labtest.v"
module labtest_tb;
 reg [3:0] In;
 wire [1:0] Out;
 wire V;
Priority_Encoder4 uut(.In(In), .Out(Out), .V(V));
initial begin
 $dumpfile("labtest_tb.vcd");
 $dumpvars(0, labtest_tb);
 In = 4'b0000;
 #10;
 In = 4'b0001;
 #10;
  In = 4'b0010;
 #10;
  In = 4'b0011;
 #10;
  In = 4'b0100;
 #10;
  In = 4'b0101;
 #10;
  In = 4'b0110;
 #10;
  In = 4'b0111;
 #10;
  In = 4'b1000;
 #10;
  In = 4'b1001;
 #10;
  In = 4'b1010;
 #10;
  In = 4'b1011;
 #10;
  In = 4'b1100;
 #10;
  In = 4'b1101;
 #10;
  In = 4'b1110;
 #10;
  In = 4'b1111;
 #10;
 end
endmodule

verilog_files/Labtest/labtest_tb.vcd
$date
	Tue Jul 20 11:38:16 2021
$end
$version
	Icarus Verilog
$end
$timescale
	1ns
$end
$scope module labtest_tb $end
$var wire 1 ! V $end
$var wire 2 " Out [1:0] $end
$var reg 4 # In [3:0] $end
$scope module uut $end
$var wire 4 $ In [3:0] $end
$var wire 1 ! V $end
$var wire 1 % tempAnd $end
$var wire 2 & Out [1:0] $end
$upscope $end
$upscope $end
$enddefinitions $end
#0
$dumpvars
b10 &
1%
b0 $
b0 #
b10 "
0!
$end
#10
b0 "
b0 &
0%
1!
b1 #
b1 $
#20
b1 "
b1 &
b10 #
b10 $
#30
b11 #
b11 $
#40
1%
b10 "
b10 &
b100 #
b100 $
#50
b0 "
b0 &
0%
b101 #
b101 $
#60
b1 "
b1 &
b110 #
b110 $
#70
b111 #
b111 $
#80
1%
b11 "
b11 &
b1000 #
b1000 $
#90
0%
b1001 #
b1001 $
#100
b1010 #
b1010 $
#110
b1011 #
b1011 $
#120
1%
b1100 #
b1100 $
#130
0%
b1101 #
b1101 $
#140
b1110 #
b1110 $
#150
b1111 #
b1111 $
