verilog_files/Lab_4_Code/lab4_flight.v
module fasystem (
input wire clk,
input wire call_button,
input wire cancel_button,
output reg D
);
reg Q;
always @(posedge clk) begin
	D = (call_button) | (!cancel_button & Q);
	Q = D;
end
endmodule

verilog_files/Lab_4_Code/lab4_flight_tb.v
`timescale 1ns/1ns
`include "lab4_flight.v"
module fasystem_tb;
reg clk;
reg call_button;
reg cancel_button;
wire D;
fasystem uut( .clk(clk), .call_button(call_button), .cancel_button(cancel_button), .D(D));
always #5 clk=~clk;
initial begin
 $dumpfile("lab4_flight.vcd");
 $dumpvars(0, fasystem_tb);
 clk=0;
 call_button=0;
 cancel_button=0;
 #10; 
 call_button=1; #40;
 cancel_button=1; #15;
 call_button=0; #15;
 cancel_button=0; #25;
 call_button=1; #15;
 call_button=0; #45;
 cancel_button = 1;#15;
$finish;
end
endmodule

verilog_files/Lab_4_Code/lab4_flight_tb.vcd
$date
	Fri Jul 09 19:30:05 2021
$end
$version
	Icarus Verilog
$end
$timescale
	1ns
$end
$scope module fasystem_tb $end
$var wire 1 ! D $end
$var reg 1 " call_button $end
$var reg 1 # cancel_button $end
$var reg 1 $ clk $end
$scope module uut $end
$var wire 1 " call_button $end
$var wire 1 # cancel_button $end
$var wire 1 $ clk $end
$var reg 1 ! D $end
$var reg 1 % Q $end
$upscope $end
$upscope $end
$enddefinitions $end
#0
$dumpvars
x%
0$
0#
0"
x!
$end
#5
1$
#10
0$
1"
#15
1%
1!
1$
#20
0$
#25
1$
#30
0$
#35
1$
#40
0$
#45
1$
#50
0$
1#
#55
1$
#60
0$
#65
0%
0!
1$
0"
#70
0$
#75
1$
#80
0$
0#
#85
1$
#90
0$
#95
1$
#100
0$
#105
1%
1!
1$
1"
#110
0$
#115
1$
#120
0$
0"
#125
1$
#130
0$
#135
1$
#140
0$
#145
1$
#150
0$
#155
1$
#160
0$
#165
0%
0!
1$
1#
